{
    "experiment": "Competitor more fair",
    "experiment_id": "952650a",
    "date": "11/03/2021 at 15:16:31",
    "target_class": 1,
    "model_type": "comp-NN",
    "x0_id": 21,
    "x0": [
        32.0,
        12.0,
        6.0,
        20.0,
        310.0,
        44.0,
        50.0,
        60.0,
        0.0,
        0.0,
        40.0,
        70.0
    ],
    "iterations": 150,
    "seed": 1,
    "dataset": "adult",
    "success": true,
    "runtime": 100.47308802604675,
    "n_solutions": 6,
    "X": [
        [
            0.7497799670116962,
            0.11541019854615542,
            0.15861485121908603,
            0.831942545224864,
            0.9328357689461197,
            0.33975678884740923,
            0.9291816413867947,
            0.76785377022414,
            0.8692351435022108,
            0.20905907941823132,
            0.3442823311943318,
            0.9151321437897424
        ],
        [
            0.6101539457859146,
            0.9984191024005613,
            0.9610868689707933,
            0.9265396316966826,
            0.2144272151999561,
            0.21045779104067575,
            0.8697369088218926,
            0.3489110060998989,
            0.11828450060614115,
            0.016703132370388563,
            0.9798118389321965,
            0.6084628799479057
        ],
        [
            0.12250489439554724,
            0.6581145290465826,
            0.6059662968683985,
            0.905621237406005,
            0.5841437205520303,
            0.7112109143223793,
            0.911981766970984,
            0.3639580528968709,
            0.5713502298204539,
            0.7187445723463723,
            0.7095893201452648,
            0.278042667489694
        ],
        [
            0.6101539457859146,
            0.7197960159741176,
            0.6059662968683985,
            0.9265396316966826,
            0.2144272151999561,
            0.21045779104067575,
            0.5420261468322057,
            0.6456767485625707,
            0.30429475017916774,
            0.6699863444960071,
            0.7095893201452648,
            0.8273975708623632
        ],
        [
            0.5220450089623263,
            0.6383120056976779,
            0.9052061606619821,
            0.9265396316966826,
            0.4244483160215753,
            0.17638969940462745,
            0.5420261468322057,
            0.6456767485625707,
            0.15961202505422623,
            0.22644030592094078,
            0.8095869287030933,
            0.767505875521035
        ],
        [
            0.7497799670116962,
            0.9984191024005613,
            0.17643464147166887,
            0.905621237406005,
            0.2144272151999561,
            0.6861911972315349,
            0.024393903596324207,
            0.3639580528968709,
            0.859938395930484,
            0.13855997177528767,
            0.8972596761663998,
            0.278042667489694
        ]
    ],
    "F": [
        [
            49.2113,
            1.0,
            0.0,
            0.0,
            0.0,
            0.0,
            0.0,
            0.0,
            0.0,
            0.0,
            1.0,
            1.0,
            0.0,
            0.12999999523162842
        ],
        [
            20.3988,
            1.0,
            0.0,
            0.0,
            0.0,
            0.0,
            0.0,
            0.0,
            0.0,
            1.0,
            0.0,
            0.0,
            0.0,
            0.09000000357627869
        ],
        [
            7.47,
            1.0,
            0.0,
            1.0,
            0.0,
            0.0,
            0.0,
            0.0,
            0.0,
            0.0,
            0.0,
            0.0,
            0.0,
            0.05999999865889549
        ],
        [
            37.645700000000005,
            1.0,
            0.0,
            0.0,
            0.0,
            0.0,
            0.0,
            0.0,
            0.0,
            1.0,
            0.0,
            0.0,
            0.0,
            0.07000000029802322
        ],
        [
            33.4315,
            1.0,
            0.0,
            0.0,
            0.0,
            0.0,
            0.0,
            0.0,
            0.0,
            1.0,
            0.0,
            0.0,
            0.0,
            0.07999999821186066
        ],
        [
            11.892199999999999,
            0.0,
            0.0,
            0.0,
            0.0,
            0.0,
            0.0,
            0.0,
            0.0,
            1.0,
            0.0,
            1.0,
            0.0,
            0.10000000149011612
        ]
    ],
    "G": [
        [
            0.0,
            0.0,
            0.0
        ],
        [
            0.0,
            0.0,
            0.0
        ],
        [
            0.0,
            0.0,
            0.0
        ],
        [
            0.0,
            0.0,
            0.0
        ],
        [
            0.0,
            0.0,
            0.0
        ],
        [
            0.0,
            0.0,
            0.0
        ]
    ],
    "pheno": [
        [
            1.0,
            2.0,
            5.0,
            -1.0,
            -1.0,
            -1.0,
            3.0512856777472415,
            5.677487548092522,
            3.599771156860216,
            32.0,
            -4.031442436002948,
            3.230064879466747
        ],
        [
            5.0,
            4.0,
            -1.0,
            -1.0,
            -1.0,
            -1.0,
            2.62866074787674,
            -3.202515614410948,
            -3.7214454502115375,
            30.0,
            12.422057327237983,
            0.8439292029937118
        ],
        [
            0.0,
            -1.0,
            -1.0,
            -1.0,
            -1.0,
            -1.0,
            2.929002417227447,
            -2.8835750941640743,
            0.6956122781456742,
            310.0,
            5.426149041706381,
            -1.7270081230924363
        ],
        [
            5.0,
            4.0,
            -1.0,
            -1.0,
            -1.0,
            -1.0,
            0.2987867316636752,
            3.0877964693888806,
            -1.9079822870298826,
            39.0,
            5.426149041706381,
            2.5474187221716544
        ],
        [
            5.0,
            4.0,
            -1.0,
            -1.0,
            -1.0,
            -1.0,
            0.2987867316636752,
            3.0877964693888806,
            -3.318532474264649,
            33.0,
            8.015030610065484,
            2.0814127416958863
        ],
        [
            2.0,
            4.0,
            -1.0,
            -1.0,
            -1.0,
            -1.0,
            -3.381342374097322,
            -2.8835750941640743,
            3.509134703775377,
            31.0,
            10.284828490520766,
            -1.7270081230924363
        ]
    ],
    "tweaked_res": [
        [
            74.6,
            12.0,
            6.0,
            20.0,
            310.0,
            44.0,
            50.0,
            60.0,
            0.0,
            2284.313,
            83.27,
            70.0
        ],
        [
            43.13,
            12.0,
            6.0,
            20.0,
            310.0,
            44.0,
            50.0,
            60.0,
            92687.82,
            0.0,
            40.0,
            70.0
        ],
        [
            46.94,
            12.0,
            13.47,
            20.0,
            310.0,
            44.0,
            50.0,
            60.0,
            0.0,
            0.0,
            40.0,
            70.0
        ],
        [
            65.597,
            12.0,
            6.0,
            20.0,
            310.0,
            44.0,
            50.0,
            60.0,
            40487.49,
            0.0,
            40.0,
            70.0
        ],
        [
            59.451,
            12.0,
            6.0,
            20.0,
            310.0,
            44.0,
            50.0,
            60.0,
            59804.563,
            0.0,
            40.0,
            70.0
        ],
        [
            32.0,
            12.0,
            6.0,
            20.0,
            310.0,
            44.0,
            50.0,
            60.0,
            76740.777,
            0.0,
            82.181,
            70.0
        ]
    ],
    "summed_costs": [
        [
            49.2113
        ],
        [
            20.3988
        ],
        [
            7.47
        ],
        [
            37.645700000000005
        ],
        [
            33.4315
        ],
        [
            11.892199999999999
        ]
    ],
    "summed_costs_discounted": [
        [
            49.2113
        ],
        [
            19.529850000000003
        ],
        [
            5.228999999999999
        ],
        [
            37.266134375
        ],
        [
            32.870828125
        ],
        [
            7.335703125
        ]
    ]
}